omr/__init__.py
omr/py.typed
omr/backends/__init__.py
omr/backends/wasapi.py
omr/cli/__init__.py
omr/cli/main.py
omr/cli/commands/__init__.py
omr/cli/commands/config.py
omr/cli/commands/devices.py
omr/cli/commands/record.py
omr/config/__init__.py
omr/config/settings.py
omr/core/__init__.py
omr/core/aec_processor.py
omr/core/audio_capture.py
omr/core/device_errors.py
omr/core/device_manager.py
omr/core/encoder.py
omr/core/input_handler.py
omr/core/mixer.py
omni_meeting_recorder-0.7.2.dist-info/METADATA
omni_meeting_recorder-0.7.2.dist-info/WHEEL
omni_meeting_recorder-0.7.2.dist-info/entry_points.txt
omni_meeting_recorder-0.7.2.dist-info/licenses/LICENSE
omni_meeting_recorder-0.7.2.dist-info/RECORD
