Metadata-Version: 2.4
Name: omni-meeting-recorder
Version: 0.7.2
Summary: CLI tool for recording online meeting audio (mic + system sound)
Project-URL: Homepage, https://github.com/dobachi/omni-meeting-recorder
Project-URL: Documentation, https://github.com/dobachi/omni-meeting-recorder#readme
Project-URL: Repository, https://github.com/dobachi/omni-meeting-recorder.git
Project-URL: Issues, https://github.com/dobachi/omni-meeting-recorder/issues
Project-URL: Changelog, https://github.com/dobachi/omni-meeting-recorder/blob/main/CHANGELOG.md
Author: dobachi
License-Expression: MIT
License-File: LICENSE
Keywords: audio,loopback,meeting,recording,wasapi
Classifier: Development Status :: 3 - Alpha
Classifier: Environment :: Console
Classifier: Intended Audience :: End Users/Desktop
Classifier: License :: OSI Approved :: MIT License
Classifier: Operating System :: Microsoft :: Windows
Classifier: Programming Language :: Python :: 3
Classifier: Programming Language :: Python :: 3.11
Classifier: Programming Language :: Python :: 3.12
Classifier: Programming Language :: Python :: 3.13
Classifier: Topic :: Multimedia :: Sound/Audio :: Capture/Recording
Requires-Python: <3.14,>=3.11
Requires-Dist: lameenc>=1.6.0
Requires-Dist: pyaec>=1.0.0
Requires-Dist: pyaudiowpatch>=0.2.12; sys_platform == 'win32'
Requires-Dist: pydantic>=2.0
Requires-Dist: rich>=13.0
Requires-Dist: typer>=0.9.0
Provides-Extra: build
Requires-Dist: pyinstaller>=6.0; extra == 'build'
Provides-Extra: dev
Requires-Dist: mypy>=1.0; extra == 'dev'
Requires-Dist: pytest-cov>=4.0; extra == 'dev'
Requires-Dist: pytest>=7.0; extra == 'dev'
Requires-Dist: ruff>=0.1.0; extra == 'dev'
Requires-Dist: taskipy>=1.12.0; extra == 'dev'
Provides-Extra: flac
Requires-Dist: pyflac>=2.2.0; extra == 'flac'
